scui/__init__.py
scui/scui.py
scui/dist/about.html
scui/dist/favicon.png
scui/dist/index.html
scui/dist/robots.txt
scui/dist/_app/version.json
scui/dist/_app/immutable/assets/0.ff4ae4b6.css
scui/dist/_app/immutable/assets/2.265a38f0.css
scui/dist/_app/immutable/assets/_layout.37ad18fa.css
scui/dist/_app/immutable/assets/_page.265a38f0.css
scui/dist/_app/immutable/assets/fira-mono-all-400-normal.1e3b098c.woff
scui/dist/_app/immutable/assets/fira-mono-cyrillic-400-normal.c7d433fd.woff2
scui/dist/_app/immutable/assets/fira-mono-cyrillic-ext-400-normal.3df7909e.woff2
scui/dist/_app/immutable/assets/fira-mono-greek-400-normal.a8be01ce.woff2
scui/dist/_app/immutable/assets/fira-mono-greek-ext-400-normal.9e2fe623.woff2
scui/dist/_app/immutable/assets/fira-mono-latin-400-normal.e43b3538.woff2
scui/dist/_app/immutable/assets/fira-mono-latin-ext-400-normal.6bfabd30.woff2
scui/dist/_app/immutable/assets/github.1ea8d62e.svg
scui/dist/_app/immutable/assets/svelte-logo.87df40b8.svg
scui/dist/_app/immutable/assets/svelte-welcome.6c300099.png
scui/dist/_app/immutable/assets/svelte-welcome.c18bcf5a.webp
scui/dist/_app/immutable/chunks/index.1ef1b067.js
scui/dist/_app/immutable/chunks/index.74c8f702.js
scui/dist/_app/immutable/chunks/singletons.8e1a18da.js
scui/dist/_app/immutable/chunks/stores.bcdfbd99.js
scui/dist/_app/immutable/entry/app.6a6c1281.js
scui/dist/_app/immutable/entry/start.07da04c9.js
scui/dist/_app/immutable/nodes/0.11a3a997.js
scui/dist/_app/immutable/nodes/1.82428d88.js
scui/dist/_app/immutable/nodes/2.d322789f.js
scui/dist/_app/immutable/nodes/3.92bb7aee.js
scui-0.0.2.dist-info/METADATA
scui-0.0.2.dist-info/WHEEL
scui-0.0.2.dist-info/entry_points.txt
scui-0.0.2.dist-info/top_level.txt
scui-0.0.2.dist-info/RECORD
