Metadata-Version: 2.1
Name: scui
Version: 0.0.2
Summary: Demo static svelte UI distributed as a python package.
Author-email: Jürgen Leschner <jldec@users.noreply.github.com>
Project-URL: Home, https://github.com/jldec/scui
Classifier: License :: OSI Approved :: MIT License
Requires-Dist: aiohttp
